LICENSE
README.md
pyproject.toml
setup.py
cpg_workflows/__init__.py
cpg_workflows/batch.py
cpg_workflows/defaults.toml
cpg_workflows/filetypes.py
cpg_workflows/inputs.py
cpg_workflows/metamist.py
cpg_workflows/resources.py
cpg_workflows/status.py
cpg_workflows/targets.py
cpg_workflows/utils.py
cpg_workflows/workflow.py
cpg_workflows.egg-info/PKG-INFO
cpg_workflows.egg-info/SOURCES.txt
cpg_workflows.egg-info/dependency_links.txt
cpg_workflows.egg-info/entry_points.txt
cpg_workflows.egg-info/requires.txt
cpg_workflows.egg-info/top_level.txt
cpg_workflows/dataproc_scripts/__init__.py
cpg_workflows/dataproc_scripts/mt_to_es.py
cpg_workflows/dataproc_scripts/pca_runner.py
cpg_workflows/jobs/__init__.py
cpg_workflows/jobs/align.py
cpg_workflows/jobs/align_rna.py
cpg_workflows/jobs/bam_to_cram.py
cpg_workflows/jobs/bcftools.py
cpg_workflows/jobs/count.py
cpg_workflows/jobs/exomiser.py
cpg_workflows/jobs/fastqc.py
cpg_workflows/jobs/fraser.py
cpg_workflows/jobs/gatk_sv.py
cpg_workflows/jobs/gcloud_composer.py
cpg_workflows/jobs/gcnv.py
cpg_workflows/jobs/genotype.py
cpg_workflows/jobs/happy.py
cpg_workflows/jobs/joint_genotyping.py
cpg_workflows/jobs/markdups.py
cpg_workflows/jobs/mito.py
cpg_workflows/jobs/multiqc.py
cpg_workflows/jobs/outrider.py
cpg_workflows/jobs/picard.py
cpg_workflows/jobs/ploidy_table_from_ped.py
cpg_workflows/jobs/sample_batching.py
cpg_workflows/jobs/samtools.py
cpg_workflows/jobs/seqr_loader.py
cpg_workflows/jobs/seqr_loader_snps_indels.py
cpg_workflows/jobs/seqr_loader_sv.py
cpg_workflows/jobs/simple_vep_annotation.py
cpg_workflows/jobs/somalier.py
cpg_workflows/jobs/stripy.py
cpg_workflows/jobs/trim.py
cpg_workflows/jobs/validation.py
cpg_workflows/jobs/vcf.py
cpg_workflows/jobs/vep.py
cpg_workflows/jobs/verifybamid.py
cpg_workflows/jobs/vqsr.py
cpg_workflows/large_cohort/__init__.py
cpg_workflows/large_cohort/ancestry_pca.py
cpg_workflows/large_cohort/ancestry_plots.py
cpg_workflows/large_cohort/browser_prepare.py
cpg_workflows/large_cohort/combiner.py
cpg_workflows/large_cohort/compute_stats_for_all_sites.py
cpg_workflows/large_cohort/convert_siteonly_ht_to_vcf_shards.py
cpg_workflows/large_cohort/dataproc_script.py
cpg_workflows/large_cohort/dataproc_utils.py
