Metadata-Version: 2.4
Name: cpg_workflows
Version: 1.38.0
Summary: CPG workflows for Hail Batch
Home-page: https://github.com/populationgenomics/production-pipelines
License: MIT
Keywords: bioinformatics
Classifier: Environment :: Console
Classifier: Intended Audience :: Science/Research
Classifier: License :: OSI Approved :: MIT License
Classifier: Natural Language :: English
Classifier: Operating System :: MacOS :: MacOS X
Classifier: Operating System :: POSIX
Classifier: Operating System :: Unix
Classifier: Programming Language :: Python
Classifier: Topic :: Scientific/Engineering
Classifier: Topic :: Scientific/Engineering :: Bio-Informatics
License-File: LICENSE
Requires-Dist: cpg-utils>=5.4.2
Requires-Dist: cyvcf2==0.30.18
Requires-Dist: analysis-runner>=2.43.3
Requires-Dist: hail>=0.2.133
Requires-Dist: networkx>=2.8.3
Requires-Dist: obonet>=0.3.1
Requires-Dist: grpcio-status<1.50,>=1.48
Requires-Dist: onnx
Requires-Dist: onnxruntime
Requires-Dist: skl2onnx
Requires-Dist: metamist>=6.9.0
Requires-Dist: pandas
Requires-Dist: peddy>=0.4.8
Requires-Dist: pyfaidx>=0.8.1.1
Requires-Dist: fsspec
Requires-Dist: slack_sdk
Requires-Dist: elasticsearch==8.*
Requires-Dist: coloredlogs
Requires-Dist: bokeh
Requires-Dist: numpy
Requires-Dist: click
Requires-Dist: tenacity
Requires-Dist: toml
Provides-Extra: test
Requires-Dist: pytest; extra == "test"
Requires-Dist: pytest-xdist; extra == "test"
Requires-Dist: pytest-mock; extra == "test"
Requires-Dist: coverage; extra == "test"
Dynamic: classifier
Dynamic: description
Dynamic: description-content-type
Dynamic: home-page
Dynamic: keywords
Dynamic: license
Dynamic: license-file
Dynamic: provides-extra
Dynamic: requires-dist
Dynamic: summary
